longai/__init__.py
longai/api.py
longai-0.1.1.dist-info/METADATA
longai-0.1.1.dist-info/WHEEL
longai-0.1.1.dist-info/top_level.txt
longai-0.1.1.dist-info/RECORD
